PyMergeMail/__init__.py
PyMergeMail/color_print.py
PyMergeMail/context.py
PyMergeMail/cred.py
PyMergeMail/main.py
PyMergeMail/result.py
PyMergeMail/setup_msg.py
PyMergeMail/split.py
PyMergeMail/template.py
PyMergeMail-0.0.1a4.dist-info/METADATA
PyMergeMail-0.0.1a4.dist-info/WHEEL
PyMergeMail-0.0.1a4.dist-info/entry_points.txt
PyMergeMail-0.0.1a4.dist-info/top_level.txt
PyMergeMail-0.0.1a4.dist-info/RECORD
