Metadata-Version: 2.1
Name: PyMergeMail
Version: 0.0.1a4
Summary: A simple module to send bulk personalized html mail with jinja2 template
Author-email: Indranil <indranilchowdhury0@gmail.com>
Project-URL: Homepage, https://github.com/Indranil012/PyMergeMail
Keywords: email,html,mail,merge
Classifier: License :: OSI Approved :: MIT License
Classifier: Programming Language :: Python
Classifier: Programming Language :: Python :: 3
Requires-Python: >=3.9
Requires-Dist: pandas
Requires-Dist: jinja2
Requires-Dist: tqdm
